{"topic_id":5782,"word_level_id":1,"tag_id":0,"word":"replacement","word_audio":"replacement.mp3","image_file":"i_1_5782_0_4_150919160953.jpg","accent":"/rɪˈpleɪsmənt/","mean_cn":"n. 代替物；接替者；更换","mean_en":"a thing that replaces something, especially because the first thing is old, broken, etc.","word_etyma":"replace复职；代替+ment表名词 → 替代","short_phrase":"replacement for unhealthy snacks","deformation_img":"d_1_5782_0_2_20150808124407.png","sentence":"The new bulb is the replacement of the old one.","sentence_trans":"那个新灯泡将要替换那个旧灯泡。","sentence_phrase":"the replacement of","sentence_audio":"sa_1_5782_0_4_150923123901.aac","cloze_data":{"syllable":"re-place-ment","cloze":"re-place-m[en]t","options":["in|on|un|an|e|i|a|o|u"],"tips":[["cem[en]t","dem[en]t"]]}}