{"topic_id":9934,"word_level_id":4,"tag_id":0,"word":"humanist","word_audio":"humanist.mp3","word_variants":"humanistic,humanistically","image_file":"20121022_03_09_13_572.jpg","accent":"/ˈhjuːmənɪst/","mean_cn":"n. 人道主义者，人类学者，人文学者；  adj. 人文主义的，人道主义的","mean_en":" a classical scholar or student of the liberal arts","word_etyma":"human 人类+ ist 表示某种主义或某种信仰者 → n. 人道主义者；人类学者，人文学者；人文主义者\r\nadj. 人文主义的；人道主义的","short_phrase":"Humanists love everyone.","sentence":"Humanists believe we can all live in peace without religion.","sentence_trans":"人道主义者相信没有宗教我们可以和平相处。","sentence_audio":"sa_4_9934_0_2_20150808182442.aac","cloze_data":{"syllable":"hu-man-ist","cloze":"hu-m[an]-ist","options":["en|in|on|un|e|i|a|o|u"],"tips":[["m[an]","Om[an]"]]}}