{"topic_id":5054,"word_level_id":1,"tag_id":0,"word":"learned","word_audio":"3_41_20170331165316_20975_c.mp3","word_variants":"learnedly,learnedness","image_file":"i_1_5054_0_7_151109150023.jpg","accent":"/ˈlɜːrnɪd/","mean_cn":"adj. 有学问的，博学的","mean_en":"having or showing a lot of learning, education, or knowledge","word_etyma":"learn学习+ed形容词后缀 → 有学问的；学术上的","short_phrase":"a learned dog","deformation_img":"d_1_5054_0_3_20150808123411.png","deformation_desc":"快看，一直学会了写字的猴子！","sentence":"The man on the stage is a well learned professor.","sentence_trans":"站在台上的是一名学识渊博的教授。","sentence_phrase":"well learned professor","sentence_audio":"3_41_20170331165317_65838_c.aac","cloze_data":{"syllable":"learned","cloze":"l[ear]ned","options":["eer|ier|eir|air"],"tips":[["l[ear]nedly","unl[ear]ned"]]}}