{"topic_id":1115,"word_level_id":1,"tag_id":0,"word":"experimental","word_audio":"experimental.mp3","word_variants":"experimentally","image_file":"i_1_1115_0_3_20150808121633.jpg","accent":"/ɪkˌsperɪˈmentl/","mean_cn":"adj. 实验（性）的，试验的","mean_en":"relating to or based on experiments","word_etyma":"experiment实验 + al形容词后缀 → experimental 实验的","short_phrase":"working on an experimental medicine","deformation_img":"d_1_1115_0_3_20150808121633.png","sentence":"Scientists aim at finding experimental evidence from experiments.","sentence_trans":"科学家们致力于从实验中找到证据。","sentence_phrase":"experimental evidence","sentence_audio":"sa_1_1115_0_3_20150808121633.aac","cloze_data":{"syllable":"ex-pe-ri-men-tal","cloze":"ex-pe-ri-m[en]-t[al]","options":["in|on|un|an|e|i|a|o|u","el|le|nl|ol"],"tips":[["m[en]","am[en]"],["t[al]","Apt[al]"]]}}