{"topic_id":8621,"word_level_id":4,"tag_id":0,"word":"backdrop","word_audio":"backdrop.mp3","image_file":"3_0_20170111071038_80381_c.jpg","accent":"/ˈbækdrɑːp/","mean_cn":"n. 背景幕，（事件的）背景","mean_en":"the scene or scenery that is in the background","short_phrase":"blue sky backdrop","deformation_img":"20140916_07_09_48_110_v3.png","sentence":"The backdrop is a piece of cloth that is hung behind the stage.","sentence_trans":"背景幕是一块挂在舞台后方的布。","sentence_phrase":"","sentence_audio":"3_0_20170111071038_22967_c.aac","cloze_data":{"syllable":"back-drop","cloze":"ba[ck]-drop","options":["que|kn|ng|nk"],"tips":[["ba[ck]en","ba[ck]"]]}}