{"topic_id":12,"word_level_id":14,"tag_id":0,"word":"abject","word_audio":"abject.mp3","word_variants":"abjectly,abjectness","image_file":"3_0_20161228070853_59791_c.jpg","accent":"/ˈæbdʒekt/","mean_cn":"adj. 卑鄙的，可怜的，不幸的","mean_en":"extremely bad or severe","word_etyma":"ab离开 + ject抛 → 都抛光了,没了 → abject 可怜的,凄惨的","short_phrase":"an abject failure","sentence":"This cat is so abject because its bowl is almost empty of food.","sentence_trans":"这只小猫太可怜了，因为它的盘子里几乎没有任何食物了。","sentence_phrase":"","sentence_audio":"3_0_20161228070853_46162_c.aac","cloze_data":{"syllable":"ab-ject","cloze":"ab-j[e]ct","options":["a|i|o|u"],"tips":[["ej[e]ct","adj[e]ct"]]}}