{"topic_id":8934,"word_level_id":1,"tag_id":0,"word":"soccer","word_audio":"soccer.mp3","image_file":"1426085957141.jpg","accent":"/ˈsɑːkər/","mean_cn":"n. 足球","mean_en":"a game played between two teams of 11 players in which a round ball is moved toward a goal usually by kicking","short_phrase":"play soccer","deformation_img":"20121225_19_16_40_269.png","sentence":"My favorite sports is soccer.","sentence_trans":"我最喜欢的运动是足球。","sentence_audio":"sa_1_8934_0_2_20150808131018.aac","cloze_data":{"syllable":"soc-cer","cloze":"socc[er]","options":["ar|ir|or|ur|a"],"tips":[[]]}}