{"topic_id":11290,"word_level_id":12,"tag_id":0,"word":"impressionable","word_audio":"impressionable.mp3","word_variants":"impressionability","image_file":"3_0_20160911070758_80894_c.jpg","accent":"/ɪmˈpreʃənəbl/","mean_cn":"adj. 敏感的，易受影响的","mean_en":"easy to influence","word_etyma":"im 入 + press 挤压 + ion表名词，情况 + able 具有某种性质的 → adj. 敏感的；易受影响的","short_phrase":"impressionable young children","sentence":"TV shows can easily influence impressionable kids.","sentence_trans":"电视节目能够轻易影响易受影响的孩子们。","sentence_phrase":"","sentence_audio":"3_0_20160911070758_83075_c.aac","cloze_data":{"syllable":"im-pres-sion-able","cloze":"im-press[ion]-able","options":["ing|ang|ong|ung"],"tips":[["press[ion]","express[ion]"]]}}