{"topic_id":5686,"word_level_id":1,"tag_id":0,"word":"attach","word_audio":"attach.mp3","word_variants":"attachable,attachment,attached,attaching,attaches","image_file":"20120514_04_46_31_314.jpg","accent":"/əˈtætʃ/","mean_cn":"v. 缚；系；贴；附上；使附属","mean_en":"to fasten or join one thing","word_etyma":"","short_phrase":"be attached to the suitcase","deformation_img":"20130106_14_37_00_807.png","sentence":"You should attach your name tag to your luggage.","sentence_trans":"你应该把你的名字系在行李上。","sentence_phrase":"attach your name tag to","sentence_audio":"sa_1_5686_0_3_20150808124225.aac","cloze_data":{"syllable":"at-tach","cloze":"atta[ch]","options":["sch|sh|th|tr|dr|gh|ion|ck|ing|in|c"],"tips":[["bran[ch]","en-ri[ch]"]]}}