{"topic_id":6838,"word_level_id":1,"tag_id":0,"word":"weed","word_audio":"weed.mp3","word_variants":"weeded,weeding,weeds","image_file":"i_1_6838_0_5_20150808125542.jpg","accent":"/wiːd/","mean_cn":"n. 杂草，野草","mean_en":"an unwanted wild plant, especially one which prevents crops or garden flowers from growing properly","short_phrase":"weeds and grass","deformation_img":"20141015_16_16_34_974_v3.png","sentence":"The worker is getting rid of the weeds.","sentence_trans":"工人正在除草。","sentence_audio":"sa_1_6838_0_5_20150808125542.aac","cloze_data":{"syllable":"weed","cloze":"w[ee]d","options":["ea|ie|ii|ye|e"],"tips":[["inw[ee]d","w[ee]ded"]]}}