{"topic_id":6133,"word_level_id":1,"tag_id":0,"word":"musical","word_audio":"musical.mp3","word_variants":"musically","image_file":"20120503_04_03_59_407.jpg","accent":"/ˈmjuːzɪkl/","mean_cn":"adj. 音乐的，悦耳的，有音乐才能的，喜欢音乐的；  n. 音乐片，音乐喜剧","mean_en":"pleasing qualities of music","word_etyma":"music音乐 + al形容词后缀 → musical 音乐的","short_phrase":"a musical instrument","deformation_img":"20141012_05_31_42_563_v3.png","sentence":"The guitar is a musical instrument which is hard to learn.","sentence_trans":"吉他是一种难学的乐器。","sentence_phrase":"a musical instrument","sentence_audio":"sa_1_6133_0_4_20150808124711.aac","cloze_data":{"syllable":"mu-si-cal","cloze":"mu-si-c[al]","options":["el|le|nl|ol"],"tips":[["Uc[al]","c[al]"]]}}