{"topic_id":3998,"word_level_id":1,"tag_id":0,"word":"coverage","word_audio":"coverage.mp3","image_file":"i_1_3998_0_4_151027093338.jpg","accent":"/ˈkʌvərɪdʒ/","mean_cn":"n. 新闻报道，覆盖范围，承保范围","mean_en":"the reporting of news and sport in newspapers and on the radio and television","word_etyma":"cover覆盖 + age名词后缀 → coverage 覆盖范围","short_phrase":"news coverage of the event","deformation_img":"d_1_3998_0_2_20150808122215.png","sentence":"All of the media coverage is just about the lottery winner.","sentence_trans":"所有的新闻报道都是关于那个中彩票的人。","sentence_phrase":"the media coverage","sentence_audio":"sa_1_3998_0_4_151106170406.aac","cloze_data":{"syllable":"cov-er-age","cloze":"cov-er-a[ge]","options":["gue|dge|geo|dj"],"tips":[["a[ge]","ima[ge]"]]}}