{"topic_id":18553,"word_level_id":13,"tag_id":0,"word":"ascription","word_audio":"ascription.mp3","image_file":"i_13_18553_0_2_20150808205513.jpg","accent":"/əˈskrɪpʃn/","mean_cn":"n. 归属，归因，赞美上帝的话","mean_en":"the act of ascribing","word_etyma":"a去 + script 写+ ion 表名词 →归属；归因","short_phrase":"ascription of the blame to him","sentence":"Her ascription of the blame to me was totally unwarranted--I didn\u0027t do it!","sentence_trans":"她对我的责备根本毫无依据--我根本就没做过！","sentence_audio":"sa_13_18553_0_2_20150808205513.aac","cloze_data":{"syllable":"as-crip-tion","cloze":"as-crip-t[ion]","options":["ing|ang|ong|ung"],"tips":[["act[ion]","dat[ion]"]]}}