{"topic_id":6619,"word_level_id":13,"tag_id":0,"word":"firework","word_audio":"firework.mp3","image_file":"20120606_03_18_16_2.jpg","accent":"/ˈfaɪərwɜːrk/","mean_cn":"n. 爆竹，烟火","mean_en":"a small device that explodes to make a display of light and noise","short_phrase":"fireworks in the sky","deformation_img":"20140815_22_43_29_382_v3.png","sentence":"I saw a lot of fireworks during the Spring  Festival holiday. ","sentence_trans":"春节期间，我看到了很多烟火爆竹。","sentence_audio":"sa_13_6619_0_3_20150808191722.aac","cloze_data":{"syllable":"fire-work","cloze":"f[ire]-work","options":["are|ere|ore|ure"],"tips":[["bef[ire]","ref[ire]"]]}}