{"topic_id":16194,"word_level_id":14,"tag_id":0,"word":"anomalous","word_audio":"anomalous.mp3","image_file":"i_14_16194_0_3_20150808180900.jpg","accent":"/əˈnɑːmələs/","mean_cn":"adj. 反常的，不规则的，不恰当的","mean_en":"not expected or usual","word_etyma":"a不+nomal正常的+ous...的→异常的；不规则的","short_phrase":"an anomalous red arrow","deformation_img":"20140822_15_14_42_153_v3.png","sentence":"That red arrow is anomalous, since all the others are differently colored.","sentence_trans":"这个红色箭头是不规则的，因为其他所有箭头都是另瓦一个颜色。","sentence_audio":"sa_14_16194_0_3_20150808180900.aac","cloze_data":{"syllable":"anom-alous","cloze":"anom-[al]ous","options":["el|le|nl|ol"],"tips":[["anom[al]ously","isanom[al]ous"]]}}