{"topic_id":20546,"word_level_id":56,"tag_id":0,"word":"impatiently","word_audio":"impatiently.mp3","image_file":"i_56_20546_0_3_20150809004444.jpg","accent":"/ɪmˈpeɪʃntli/","mean_cn":"adv. 不耐烦地，急躁地","sentence":"He waited impatiently for her to get ready.","sentence_trans":"他很不耐烦地等她准备好。","sentence_audio":"sa_56_20546_0_3_20150809004444.aac","cloze_data":{"syllable":"im-pa-tient-ly","cloze":"im-p[a]-t[ie]nt-ly","options":["e|i|o|u","ea|ee|ii|ye|e"],"tips":[["p[a]","dep[a]"],["pat[ie]nt","sit[ie]nt"]]}}