{"topic_id":7356,"word_level_id":9,"tag_id":0,"word":"celluloid","word_audio":"celluloid.mp3","image_file":"i_9_7356_0_2_20150808154340.jpg","accent":"/ˈseljulɔɪd/","mean_cn":"n. 赛璐珞，电影（胶片）","mean_en":"a tough kind of plastic that was used in the past to make photographic film and other products","short_phrase":"roll of celluloid film","sentence":"Did you know films are still made on celluloid?","sentence_trans":"你知道吗？电影仍然是靠电影胶片制成的。","sentence_audio":"sa_9_7356_0_2_20150808154340.aac","cloze_data":{"syllable":"Cel-lu-loid","cloze":"C[el]lu-loid","options":["al|le|nl|ol"],"tips":[["C[el]lucotton","C[el]lulomonas"]]}}