{"topic_id":18728,"word_level_id":18,"tag_id":0,"word":"bossy","word_audio":"bossy.mp3","image_file":"i_18_18728_0_2_20150808204024.jpg","accent":"/ˈbɔːsi/","mean_cn":"adj. 专横的，浮雕装饰的，爱指挥他人的；  n. 母牛，牛犊","mean_en":"tending too often to tell people what to do :often giving orders in a way that people do not like","short_phrase":"the big, bossy businessman","sentence":"I don\u0027t like it when my boss is so, well... bossy!","sentence_trans":"我不喜欢我老板很专横的时候！","sentence_audio":"sa_18_18728_0_2_20150808204024.aac","cloze_data":{"syllable":"bossy","cloze":"b[o]ssy","options":["a|e|i|u"],"tips":[[]]}}