{"topic_id":8828,"word_level_id":4,"tag_id":0,"word":"hatchet","word_audio":"hatchet.mp3","image_file":"i_4_8828_0_3_20150808174332.jpg","accent":"/ˈhætʃɪt/","mean_cn":"n. 短柄小斧；  vt. 扼杀","mean_en":"a small ax that has a short handle","short_phrase":"hatchets are weapons","deformation_img":"20140728_12_00_19_831_v3.png","sentence":"I use this hatchet to cut wood.","sentence_trans":"我用这把短斧砍木头。","sentence_audio":"sa_4_8828_0_3_20150808174332.aac","cloze_data":{"syllable":"hatch-et","cloze":"ha[tch]-et","options":["chr|sch|th|sh"],"tips":[["ha[tch]el","ha[tch]er"]]}}