{"topic_id":6776,"word_level_id":1,"tag_id":0,"word":"waiter","word_audio":"waiter.mp3","image_file":"i_1_6776_0_2_20150808125454.jpg","accent":"/ˈweɪtər/","mean_cn":"n. 侍者，服务员","mean_en":"a man who serves food or drinks to people in a restaurant","word_etyma":"wait等待+er名词后缀 → 等待着的人 →侍者","short_phrase":"The waiter brings us food.","deformation_img":"d_1_6776_0_2_20150808125454.png","sentence":"I\u0027ll be your waiter tonight - may I recommend the fish?","sentence_trans":"今晚我是你的侍者，我可以推荐鱼吗？","sentence_audio":"sa_1_6776_0_2_20150808125454.aac","cloze_data":{"syllable":"wait-er","cloze":"wait-[er]","options":["ar|ir|or|ur|a"],"tips":[["[er]","o[er]"]]}}