{"topic_id":15971,"word_level_id":14,"tag_id":0,"word":"oration","word_audio":"oration.mp3","image_file":"20120523_05_24_43_489.jpg","accent":"/ɔːˈreɪʃn/","mean_cn":"n. 演说，致辞，叙述法","mean_en":"a formal speech","word_etyma":"orat说 + ion名词后缀 → oration 演说","short_phrase":"the speaker\u0027s oration","sentence":"The power of his oration drove his audience wild with applause.","sentence_trans":"他的演说力量驱使观众热烈鼓掌。","sentence_phrase":"The power of his oration","sentence_audio":"sa_14_15971_0_3_20150808175757.aac","cloze_data":{"syllable":"o-ra-tion","cloze":"o-ra-t[ion]","options":["ing|ang|ong|ung"],"tips":[["act[ion]","dat[ion]"]]}}