{"topic_id":4258,"word_level_id":2,"tag_id":0,"word":"petty","word_audio":"petty.mp3","word_variants":"pettily,pettier,pettiest,pettiness","image_file":"1425952643661.jpg","accent":"/ˈpeti/","mean_cn":"adj. 价值不大的；小的；器量小的；琐碎的","mean_en":"relating to things that are not very important or serious","short_phrase":"give some petty cash","deformation_img":"d_2_4258_0_3_20150808142905.png","sentence":"I hand my petty cash to the beggar.","sentence_trans":"我把零钱递给乞丐。","sentence_audio":"sa_2_4258_0_3_20150808142905.aac","cloze_data":{"syllable":"pet-ty","cloze":"p[e]tty","options":["a|i|o|u"],"tips":[["p[e]ttyfog"]]}}