{"topic_id":19342,"word_level_id":18,"tag_id":0,"word":"suckle","word_audio":"suckle.mp3","image_file":"1425952837147.jpg","accent":"/ˈsʌkl/","mean_cn":"vi. 吃奶；  vt. 给…哺乳，养育，吸吮","mean_en":"to give (a baby or young animal) milk from a breast or from an udder","short_phrase":"The babies suckle at their mother\u0027s nipples.","sentence":"This dog lets all of her seven babies suckle at once.","sentence_trans":"狗妈妈同时让它的七只宝宝吃奶。","sentence_audio":"sa_18_19342_0_2_20150808204141.aac","cloze_data":{"syllable":"suck-le","cloze":"su[ck]-le","options":["que|kn|ng|nk"],"tips":[["su[ck]","resu[ck]"]]}}