{"topic_id":8000,"word_level_id":1,"tag_id":0,"word":"excite","word_audio":"excite.mp3","word_variants":"excited,exciting,excites","image_file":"i_1_8000_0_2_20150808130259.jpg","accent":"/ɪkˈsaɪt/","mean_cn":"vt. 激动，激发，使兴奋，刺激","mean_en":"to cause feelings of enthusiasm in (someone); to make (someone) feel energetic and eager to do something","word_etyma":"ex使...出自 + cite 使开始工作 → excite 激发","short_phrase":"shopping excites her","deformation_img":"d_1_8000_0_2_20150808130259.png","deformation_desc":"看他那兴奋得手舞足蹈的样子！","sentence":"Shopping always excites girls.","sentence_trans":"购物总能让女生们感到兴奋。","sentence_phrase":"excites girls","sentence_audio":"sa_1_8000_0_2_20150808130259.aac","cloze_data":{"syllable":"ex-cite","cloze":"[e]x-cite","options":["a|i|o|u"],"tips":[["[e]x","[e]xam"]]}}