{"topic_id":17183,"word_level_id":13,"tag_id":0,"word":"key","word_audio":"key.mp3","word_variants":"keys,keyed,keying","image_file":"i_13_17183_0_2_20150808204524.jpg","accent":"/kiː/","mean_cn":"n. 钥匙，键，答案；  adj. 关键的","mean_en":"a device that is used to open a lock or start an automobile","short_phrase":"turn the key","deformation_img":"d_13_17183_0_2_20150808204524.png","sentence":"Now I have my own key to my own house\u0027s front door - it feels so good!","sentence_trans":"我终于有了自己家门的钥匙，太棒了！","sentence_audio":"sa_13_17183_0_2_20150808204524.aac","cloze_data":{"syllable":"key","cloze":"k[ey]","options":["aa|ai|ei|ay|aw|a"],"tips":[["unk[ey]","donk[ey]"]]}}