{"topic_id":18543,"word_level_id":19,"tag_id":0,"word":"onomatopoeia","word_audio":"onomatopoeia.mp3","image_file":"i_19_18543_0_3_20150808191028.jpg","accent":"/ˌɑːnəˌmætəˈpiːə/","mean_cn":"n. 拟声，拟声词","mean_en":"the creation of words that imitate natural sounds","short_phrase":"\"BOOM!\" is onomatopoeia.","sentence":"Onomatopoeia means words like Pop, Puff, Boom, or Crash that sound like what they mean.","sentence_trans":"拟声词指“砰”噗““隆隆”哗啦”这种词，听起来就像它们表达的意思。","sentence_audio":"sa_19_18543_0_3_20150808191028.aac","cloze_data":{"syllable":"ono-matopoeia","cloze":"ono-matopo[ei]a","options":["aa|ai|ay|aw|ey|a"],"tips":[[]]}}