{"topic_id":11247,"word_level_id":12,"tag_id":0,"word":"nexus","word_audio":"nexus.mp3","word_variants":"nexus","image_file":"20120518_03_37_39_695.jpg","accent":"/ˈneksəs/","mean_cn":"n. 关系，连结","mean_en":"a relationship or connection between people or things","word_etyma":"","short_phrase":"nexus of friends","deformation_img":"20140815_22_08_37_473_v3.png","sentence":"I keep in close contact with my nexus of good friends.","sentence_trans":"我和好朋友们保持密切联系。","sentence_audio":"sa_12_11247_0_3_20150808181004.aac","cloze_data":{"syllable":"nexus","cloze":"n[e]xus","options":["a|i|o|u"],"tips":[[]]}}