{"topic_id":8418,"word_level_id":1,"tag_id":0,"word":"suffering","word_audio":"suffering.mp3","image_file":"i_1_8418_0_2_20150808130731.jpg","accent":"/ˈsʌfərɪŋ/","mean_cn":"n. 受难，苦楚；  adj. 受苦的，患病的","mean_en":"pain that is caused by injury, illness, loss, etc.; physical, mental, or emotional pain","word_etyma":"suf在下面+fer带+ ing表名词 →suffer带到下面去受苦+ing表名词\r\n → 受难","short_phrase":"Her suffering is caused by back pain.","deformation_img":"d_1_8418_0_2_20150808130731.png","sentence":"My mother\u0027s suffering is intense - her back really hurts.","sentence_trans":"我妈妈承受了很大的痛苦，她的背真的很痛。","sentence_audio":"sa_1_8418_0_2_20150808130731.aac","cloze_data":{"syllable":"suf-fer-ing","cloze":"suff[er]-ing","options":["aa|ae|ai|ao|au|ea|ee|ei|eo|eu|ia|ie|ii|io|iu|oa|oe|oi|oo|ou|ua|ue|ui|uo|uu|ay|ey|ow|oy|ur|al|ir|or|ar|a|e|i|o|u"],"tips":[["bor-d[er]","con-sid-[er]"]]}}