{"topic_id":1887,"word_level_id":11,"tag_id":0,"word":"monarchy","word_audio":"monarchy.mp3","word_variants":"monarchial,monarchies","image_file":"3_0_20160718115359_16352_c.jpg","accent":"/ˈmɑːnərki/","mean_cn":"n. 君主政体，君主国","mean_en":"a country that is ruled by a monarch (such as a king or queen)","word_etyma":"mon独+archy统治→一人统治→ 君主政体，君主制度","short_phrase":"soldiers of the English monarchy","deformation_sentence":"","deformation_sentence_trans":"","sentence":"The Queen is the head of the British monarchy.","sentence_trans":"在君主制的英国，女王是元首。","sentence_phrase":"","sentence_audio":"3_0_20160718115359_821_c.aac","cloze_data":{"syllable":"monar-chy","cloze":"mon[ar]-chy","options":["er|ir|or|ur|a"],"tips":[["pulmon[ar]","mon[ar]chal"]]}}