{"topic_id":5969,"word_level_id":1,"tag_id":0,"word":"absorb","word_audio":"3_52_20170504154248_37643_c.mp3","word_variants":"absorbable,absorbingly,absorbability,absorbed,absorbing,absorbs","image_file":"i_1_5969_0_5_20150808124610.jpg","accent":"/əbˈzɔːrb/","mean_cn":"vt. 吸收，吸引…的注意，理解，承受，吞并","mean_en":"to take in a liquid, gas or other substance from the surface or space around","word_etyma":"ab加强 + sorb吸收 → absorb 吸收","short_phrase":"","deformation_img":"20141011_13_27_30_268_v3.png","sentence":"Sponges can absorb a lot of water.","sentence_trans":"海绵可以吸收很多水。","sentence_phrase":"absorb a lot of water","sentence_audio":"3_41_20170331174142_57210_c.aac","cloze_data":{"syllable":"ab-sorb","cloze":"ab-s[or]b","options":["aa|ae|ai|ao|au|ea|ee|ei|eo|eu|ia|ie|ii|io|iu|oa|oe|oi|oo|ou|ua|ue|ui|uo|uu|ay|ey|ow|oy|ur|al|ir|er|ar|a|e|i|o|u"],"tips":[["ig-n[or]e","acc[or]d-ing"]]}}