{"topic_id":15979,"word_level_id":14,"tag_id":0,"word":"remunerate","word_audio":"remunerate.mp3","word_variants":"remunerable,remunerability,remunerated,remunerating,remunerates","image_file":"i_14_15979_0_2_20150808175832.jpg","accent":"/rɪˈmjuːnəreɪt/","mean_cn":"v. 酬劳，给与报酬，赔偿","mean_en":"to pay someone for work that has been done","word_etyma":"re 回+ muner服务+ ate 表动词→对服务的回报 → 给予报酬","short_phrase":"remunerate you for sth. with money","sentence":"This red envelope will remunerate you for all the work you have done for us.","sentence_trans":"这个红包作为你帮我们工作的酬劳。","sentence_audio":"sa_14_15979_0_2_20150808175832.aac","cloze_data":{"syllable":"re-mu-ner-ate","cloze":"re-m[u]-n[er]-ate","options":["a|e|i|o","ar|ir|or|ur|a"],"tips":[["m[u]","um[u]"],["garn[er]","corn[er]"]]}}