{"topic_id":390301,"word_level_id":196,"tag_id":0,"word":"twisting","word_audio":"wa_906_-906_0_1_160229102026.aac","image_file":"i_906_-906_0_1_160225181721.jpg","accent":"/twɪstɪŋ/","mean_cn":"adj. 扭曲的","mean_en":"bending","sentence":"The structure of the DNA looks like a twisting ladder.","sentence_trans":"基因的结构看上去像一架扭曲的梯子。","sentence_audio":"sa_906_-906_0_1_160229102037.aac","cloze_data":{"syllable":"twist-ing","cloze":"twist-[ing]","options":["ion|ang|ong|ung"],"tips":[["[ing]","ap[ing]"]]}}