{"topic_id":15951,"word_level_id":4,"tag_id":0,"word":"tutorial","word_audio":"tutorial.mp3","image_file":"i_4_15951_0_5_20150808191745.jpg","accent":"/tuːˈtɔːriəl/","mean_cn":"adj. 家庭教师的，辅导的，个别指导的；  n. 个别指导","mean_en":"a class taught by a tutor for one student or for a small group of students","word_etyma":"tut保护+or人+ial形容词后缀 → 家庭教师的，指导教师的","short_phrase":"give the students a tutorial","deformation_img":"20140824_20_56_28_729_v3.png","sentence":"The tutor give us a tutorial once a week. ","sentence_trans":"补习老师每周给我们上一节补习。","sentence_audio":"sa_4_15951_0_5_20150808191745.aac","cloze_data":{"syllable":"tu-to-ri-al","cloze":"tu-t[o]-ri-[al]","options":["a|e|i|u","el|le|nl|ol"],"tips":[["It[o]","Ot[o]"],["[al]","[al]ba"]]}}