{"topic_id":6421,"word_level_id":1,"tag_id":0,"word":"smash","word_audio":"smash.mp3","word_variants":"smasher,smashed,smashing,smashes","image_file":"i_1_6421_0_7_160324101912.jpg","accent":"/smæʃ/","mean_cn":"v. 粉碎，猛冲，击溃；  n. 破碎（声），猛撞，巨大的成功","mean_en":"to break (something) into many pieces; to shatter or destroy (something)","short_phrase":"The cars smashed into each other.","deformation_img":"20141013_10_49_32_782_v3.png","sentence":"The football smashed the glass into pieces.","sentence_trans":"这个足球把玻璃撞成了碎片。","sentence_phrase":"smashed the glass","sentence_audio":"sa_1_6421_0_7_160324103340.aac","cloze_data":{"syllable":"smash","cloze":"sma[sh]","options":["tch|chr|sch|th"],"tips":[["sma[sh]ery","sma[sh]er"]]}}