{"topic_id":18555,"word_level_id":13,"tag_id":0,"word":"prophesy","word_audio":"wa_13_18555_0_4_160326164810.aac","image_file":"i_13_18555_0_2_20150808205515.jpg","accent":"/ˈprɑːfəsaɪ/","mean_cn":"v. 预言，预报","mean_en":"to state that something will happen in the future","word_etyma":"pro 在前 + phesy \u003dspeak说→提前说→ v.预言, 预报","short_phrase":"She\u0027s about to tell a prophesy.","sentence":"I prophesy that next year you will find a wife!","sentence_trans":"我预言明年你会找到老婆。","sentence_audio":"sa_13_18555_0_4_160326164821.aac","cloze_data":{"syllable":"proph-esy","cloze":"pr[o]ph-esy","options":["a|e|i|u"],"tips":[["pr[o]phesiable","pr[o]phesier"]]}}