{"topic_id":19233,"word_level_id":14,"tag_id":0,"word":"undergird","word_audio":"undergird.mp3","image_file":"20121102_03_11_57_568.jpg","accent":"/ˌʌndə\u0027gɜːd/","mean_cn":"v. 加强，巩固……的底部","mean_en":"to strengthen or support (something) from below","short_phrase":"These steel beams undergird the building\u0027s structure.","sentence":"These steel beams undergird the building\u0027s structure.","sentence_trans":"这些钢梁巩固了这座建筑的结构。","sentence_audio":"sa_14_19233_0_2_20150808185546.aac","cloze_data":{"syllable":"un-der-gird","cloze":"un-d[er]-gird","options":["ar|ir|or|ur|a"],"tips":[["d[er]by","d[er]ma"]]}}