{"topic_id":18762,"word_level_id":13,"tag_id":0,"word":"terrible","word_audio":"terrible.mp3","image_file":"i_13_18762_0_2_20150808205550.jpg","accent":"/ˈterəbl/","mean_cn":"adj. 可怕的，极糟的，极度的","mean_en":"very shocking and upsetting","word_etyma":"terr怕 + ible形容词后缀：可...的 → terrible 可怕的","short_phrase":"What a terrible sight!","deformation_img":"d_13_18762_0_2_20150808205550.png","sentence":"Every full moon the dead rise from their graves—what a terrible sight!","sentence_trans":"每一个满月的夜晚死者都会从墓中出来——多可怕的景象！","sentence_phrase":"what a terrible sight","sentence_audio":"sa_13_18762_0_2_20150808205550.aac","cloze_data":{"syllable":"ter-ri-ble","cloze":"terri-[ble]","options":["tle|dle|ple|cle|gle|kle"],"tips":[["ca[ble]","am[ble]"]]}}