{"topic_id":626,"word_level_id":2,"tag_id":0,"word":"consul","word_audio":"consul.mp3","word_variants":"consular,consulship","image_file":"i_2_626_0_3_20150808141212.jpg","accent":"/ˈkɑːnsl/","mean_cn":"n. 领事，（古罗马的）两执政官之一，（1799～1804年间法兰西共和国的）三执政官之一","mean_en":"a government official whose job is to live in a foreign country and protect and help the citizens of his or her own country who are traveling, living, or doing business there","short_phrase":"the foreign government\u0027s consul","sentence":"She is U.S\u0027s deputy consul in UN.","sentence_trans":"她是美国驻联合国的副领事。","sentence_audio":"sa_2_626_0_3_20150808141212.aac","cloze_data":{"syllable":"con-sul","cloze":"c[on]-sul","options":["en|in|un|an|e|i|a|o|u"],"tips":[["c[on]","ic[on]"]]}}