{"topic_id":4343,"word_level_id":19,"tag_id":0,"word":"dole","word_audio":"dole.mp3","word_variants":"doled,doling,doles","image_file":"i_19_4343_0_3_20150808170200.jpg","accent":"/doʊl/","mean_cn":"n. 救济，（失业）救济金；  v. 发放，发给","mean_en":"money that a government (especially the British government) gives to people who do not have jobs or who are very poor","short_phrase":"a line to receive the dole","sentence":"The homeless line up to receive their dole.","sentence_trans":"无家可归的人排起了长队来领救济金。","sentence_phrase":"receive their dole","sentence_audio":"sa_19_4343_0_3_20150808170200.aac","cloze_data":{"syllable":"dole","cloze":"do[le]","options":["al|el|nl|ol"],"tips":[["indo[le]","condo[le]"]]}}