{"topic_id":1683,"word_level_id":4,"tag_id":0,"word":"jumble","word_audio":"jumble.mp3","word_variants":"jumbled,jumbling,jumbles","image_file":"i_4_1683_0_2_20150808144256.jpg","accent":"/ˈdʒʌmbl/","mean_cn":"v. 混杂，搞乱；  n. 混乱","mean_en":"a group of things that are not arranged in a neat or orderly way","short_phrase":"a room in a jumble","sentence":"The office was in a jumble; I couldn\u0027t find anything.","sentence_trans":"那个办公室很乱，我不能找到任何东西。","sentence_phrase":"in a jumble","sentence_audio":"sa_4_1683_0_2_20150808144256.aac","cloze_data":{"syllable":"jum-ble","cloze":"jum-[ble]","options":["tle|dle|ple|cle|gle|kle"],"tips":[["ca[ble]","am[ble]"]]}}