{"topic_id":6404,"word_level_id":1,"tag_id":0,"word":"premature","word_audio":"3_45_20170124153245_36976_c.mp3","word_variants":"prematurely,prematureness","image_file":"i_1_6404_0_2_20150808125123.jpg","accent":"/ˌpriːməˈtʃʊr/","mean_cn":"adj. 早产的，过早的，早熟的，不成熟的；  n. 早产儿","mean_en":"born before the normal time","word_etyma":"pre预先+mature成熟 → 比预期时间早的，不成熟的，仓促的","short_phrase":"a premature baby","deformation_img":"d_1_6404_0_2_20150808125123.png","sentence":"The premature baby was born one month early.","sentence_trans":"这个早产儿提前一个月出生。","sentence_phrase":"The premature baby","sentence_audio":"sa_1_6404_0_171_160220154241.aac","cloze_data":{"syllable":"pre-ma-ture","cloze":"pre-ma-t[ure]","options":["are|ere|ire|ore"],"tips":[["fut[ure]","act[ure]"]]}}