{"topic_id":10984,"word_level_id":1,"tag_id":0,"word":"wonder","word_audio":"wonder.mp3","word_variants":"wonderer,wondered,wondering,wonders","image_file":"i_1_10984_0_4_150923094611.jpg","accent":"/ˈwʌndər/","mean_cn":"v. 想知道，惊奇；  n. 奇迹，惊奇","mean_en":"to think about something and try to decide what is true, what will happen, what you should do, etc.","short_phrase":"a wonder of the ancient world","deformation_img":"d_1_10984_0_2_20150808131744.png","deformation_desc":"你想知道这个词是什么意思吗？","sentence":"The woman wonders if she carries a boy or a girl.","sentence_trans":"这个女人想知道她的宝宝是男是女。","sentence_audio":"sa_1_10984_0_4_151017115605.aac","cloze_data":{"syllable":"won-der","cloze":"won-d[er]","options":["ar|ir|or|ur|a"],"tips":[["d[er]by","d[er]ma"]]}}