{"topic_id":14618,"word_level_id":101,"tag_id":0,"word":"twitter","word_audio":"twitter.mp3","word_variants":"twittery,twitterer,twittered,twittering,twitters","image_file":"i_101_14618_0_3_20150809040331.jpg","accent":"/ˈtwɪtər/","mean_cn":"n. 鸟鸣声，喋喋不休，慌张；  v. 鸟鸣，摆动，嘁嘁喳喳地讲","mean_en":"","sentence":"No twittering allowed here!","sentence_trans":"此处禁止喧哗。","sentence_audio":"3_49_20170310150232_12121_c.aac","cloze_data":{"syllable":"twit-ter","cloze":"twitt[er]","options":["ar|ir|or|ur|a"],"tips":[["twitt[er]ly","twitt[er]er"]]}}