{"topic_id":3956,"word_level_id":13,"tag_id":0,"word":"disable","word_audio":"disable.mp3","word_variants":"disabling,disablingly,disablement,disabled,disables","image_file":"i_13_3956_0_2_20150808163612.jpg","accent":"/dɪsˈeɪbl/","mean_cn":"vt. 使无效，使不能运转，使无能，使伤残，使丧失活动能力","mean_en":"to make (someone) unable to do something (such as use part of the body) in the usual way","word_etyma":"dis不+able形容词后缀, 具有某种性质的 → 使丧失能力,伤残","short_phrase":"a sign for disabled people","deformation_img":"d_13_3956_0_2_20150808163612.png","sentence":"The absence of sun disables solar panels.","sentence_trans":"没有太阳的话，太阳能板就不运作了。","sentence_audio":"sa_13_3956_0_2_20150808163612.aac","cloze_data":{"syllable":"dis-able","cloze":"dis-a[ble]","options":["tle|dle|ple|cle|gle|kle"],"tips":[["ena[ble]","lia[ble]"]]}}