{"topic_id":3951,"word_level_id":1,"tag_id":0,"word":"throat","word_audio":"throat.mp3","word_variants":"throated,throating,throats","image_file":"i_1_3951_0_4_160324113110.jpg","accent":"/θroʊt/","mean_cn":"n. 咽喉，嗓子","mean_en":"the tube inside the neck that takes food and air down from your mouth into your body","short_phrase":"throat pain","deformation_img":"20121225_19_04_28_717.png","sentence":"I had a sore throat after I caught a cold.","sentence_trans":"我感冒后喉咙很疼。","sentence_phrase":"had a sore throat","sentence_audio":"sa_1_3951_0_4_160324102543.aac","cloze_data":{"syllable":"throat","cloze":"[th]roat","options":["tch|chr|sch|sh"],"tips":[["[th]roatful","[th]roated"]]}}