{"topic_id":10661,"word_level_id":4,"tag_id":0,"word":"presidential election","word_audio":"presidential election.mp3","image_file":"i_4_10661_0_2_20150808185813.jpg","accent":"/ˌprezɪˈdenʃ(ə)l/ /ɪˈlekʃ(ə)n/","mean_cn":"总统选举","mean_en":"an election for president","short_phrase":"the American presidential election","sentence":"There are so many political advertisements during presidential election years.","sentence_trans":"在总统选举年期间，政治广告真是太多了。","sentence_phrase":"presidential election years","sentence_audio":"sa_4_10661_0_2_20150808185813.aac"}