{"topic_id":17327,"word_level_id":13,"tag_id":0,"word":"incorrect","word_audio":"incorrect.mp3","word_variants":"incorrectly,incorrectness","image_file":"i_13_17327_0_2_20150808204737.jpg","accent":"/ˌɪnkəˈrekt/","mean_cn":"adj. 错误的，不正确的，不适当的，不真实的","mean_en":"not correct","word_etyma":"in不+cor共同+rect正确 →不正确的","short_phrase":"the incorrect answer","deformation_img":"d_13_17327_0_2_20150808204737.png","sentence":"I\u0027m sorry, your answer is close, but incorrect.","sentence_trans":"抱歉，你的答案很接近了，但还是错的。","sentence_audio":"sa_13_17327_0_2_20150808204737.aac","cloze_data":{"syllable":"in-cor-rect","cloze":"in-c[or]rect","options":["ar|er|ir|ur|a"],"tips":[["c[or]rect","c[or]rected"]]}}