{"topic_id":929,"word_level_id":14,"tag_id":0,"word":"dissonance","word_audio":"dissonance.mp3","image_file":"3_0_20161224072608_97590_c.jpg","accent":"/ˈdɪsənəns/","mean_cn":"n. 不一致，不调和，不和谐音","mean_en":" Lack of agreement, consistency, or harmony; conflict","word_etyma":"dissonan不和谐的 + ce名词后缀 → dissonance 不和谐","short_phrase":"dissonance between two people","deformation_img":"20140823_07_44_59_347_v3.png","sentence":"There is a dissonance on which kind of medicine is better between these two people.","sentence_trans":"这两个人对中药还是西药哪个好有不一致的观点。","sentence_phrase":"a dissonance on","sentence_audio":"3_0_20161224072608_96974_c.aac","cloze_data":{"syllable":"dis-so-nance","cloze":"disso-n[an]ce","options":["en|in|on|un|e|i|a|o|u"],"tips":[["ordn[an]ce","fin[an]ce"]]}}