{"topic_id":6080,"word_level_id":11,"tag_id":0,"word":"make the most of","word_audio":"make the most of.mp3","image_file":"20120620_03_05_52_679.jpg","accent":"/meɪk/ /ðə/ /moʊst/ /ɑv/","mean_cn":"v. 充分利用","mean_en":"to show or use to the best advantage","short_phrase":"make the most of one\u0027s plastic bottles","sentence":"She makes the most of her old bottles by recycling them.","sentence_trans":"她回收她的废旧瓶子并加以充分利用。","sentence_phrase":"makes the most of her old bottles","sentence_audio":"sa_11_6080_0_2_20150808164720.aac"}