{"topic_id":19747,"word_level_id":24,"tag_id":0,"word":"furthest","word_audio":"furthest.mp3","image_file":"i_24_19747_0_3_20150809002857.jpg","accent":"/ˈfɜːrðɪst/","mean_cn":"adv. 最远地，最大程度地（far的最高级）；  adj. 最远的，最遥远的（far的最高级）","mean_en":"(superlative of far) at or to the greatest distance in space or time","deformation_img":"d_24_19747_0_3_20150809002857.png","sentence":"What\u0027s the furthest thing that you can see?","sentence_trans":"你能看见最远的东西是什么？","sentence_phrase":"the furthest thing","sentence_audio":"sa_24_19747_0_3_20150809002857.aac","cloze_data":{"syllable":"fur-thest","cloze":"fur-[th]est","options":["tch|chr|sch|sh"],"tips":[["far[th]est"]]}}