{"topic_id":16687,"word_level_id":14,"tag_id":0,"word":"poach","word_audio":"poach.mp3","word_variants":"poachable,poached,poaching,poaches","image_file":"3_0_20160911071053_28852_c.jpg","accent":"/poʊtʃ/","mean_cn":"v. 水煮，偷猎，窃取","mean_en":" cook in a simmering liquid","short_phrase":"poach an egg","sentence":"Hunters poach elephants for their ivory.","sentence_trans":"猎人们为得到象牙而偷猎大象。","sentence_phrase":"","sentence_audio":"3_0_20160911071053_69359_c.aac","cloze_data":{"syllable":"poach","cloze":"p[oa]ch","options":["oe|oi|oy|oo|o"],"tips":[["p[oa]chable","p[oa]cher"]]}}