{"topic_id":3392,"word_level_id":4,"tag_id":0,"word":"cacti","word_audio":"cacti.mp3","image_file":"20120521_04_12_22_119.jpg","accent":"/\u0027kæktaɪ/","mean_cn":"n. 仙人掌","mean_en":"a thick, fleshy plant that grows in many hot, dry parts of the world","short_phrase":"the green cacti","deformation_img":"20140729_00_15_46_903_v3.png","sentence":"Many cacti have spiky skins.","sentence_trans":"许多仙人掌都长着带刺的外表。","sentence_audio":"sa_4_3392_0_3_20150808145539.aac","cloze_data":{"syllable":"cac-ti","cloze":"c[a]c-ti","options":["e|i|o|u"],"tips":[["c[a]ctoid","c[a]chaza"]]}}