{"topic_id":6376,"word_level_id":1,"tag_id":0,"word":"wicked","word_audio":"wicked.mp3","word_variants":"wickedly,wickeder,wickedest,wickedness","image_file":"i_1_6376_0_3_20150808125106.jpg","accent":"/ˈwɪkɪd/","mean_cn":"adj. 坏的，邪恶的","mean_en":"morally bad","short_phrase":"a wicked witch","deformation_img":"d_1_6376_0_3_20150808125106.png","sentence":"The wicked witch forced Snow White to drink the poison.","sentence_trans":"邪恶的巫婆强迫白雪公主喝下毒药。","sentence_phrase":"The wicked witch","sentence_audio":"sa_1_6376_0_3_20150808125106.aac","cloze_data":{"syllable":"wicked","cloze":"wi[ck]ed","options":["que|kn|ng|nk"],"tips":[["wi[ck]edlike","wi[ck]edly"]]}}