{"topic_id":16963,"word_level_id":14,"tag_id":0,"word":"charlatan","word_audio":"charlatan.mp3","word_variants":"charlatanic,charlatanism","image_file":"i_14_16963_0_3_20150808183820.jpg","accent":"/ˈʃɑːrlətən/","mean_cn":"n. 骗子，假内行","mean_en":"a person who falsely pretends to know or be something in order to deceive people","deformation_img":"20140814_21_41_24_307_v3.png","sentence":"I don\u0027t believe that salesman - I think he\u0027s just a charlatan.","sentence_trans":"我不相信那个推销员，我觉得他只是个骗子。","sentence_audio":"sa_14_16963_0_3_20150808183820.aac","cloze_data":{"syllable":"char-la-tan","cloze":"ch[ar]-la-tan","options":["er|ir|or|ur|a"],"tips":[["ch[ar]ka","ch[ar]er"]]}}