{"topic_id":7076,"word_level_id":4,"tag_id":0,"word":"eternally","word_audio":"eternally.mp3","image_file":"i_4_7076_0_2_20150808164755.jpg","accent":"/ɪˈtɜːrnəli/","mean_cn":"adv. 永恒地，不朽地","mean_en":"for a limitless time","short_phrase":"","sentence":"I will love you eternally, my dear. ","sentence_trans":"我会永远爱你，亲爱的。","sentence_phrase":"love you eternally","sentence_audio":"sa_4_7076_0_2_20150808164755.aac","cloze_data":{"syllable":"eter-nal-ly","cloze":"eter-n[all]y","options":["ald|alk|alm|alt|ial"],"tips":[["fin[all]y","ban[all]y"]]}}