{"topic_id":15436,"word_level_id":13,"tag_id":0,"word":"daunt","word_audio":"daunt.mp3","word_variants":"dauntingly,daunter,daunted,daunting,daunts","image_file":"i_13_15436_0_2_20150808203358.jpg","accent":"/dɔːnt/","mean_cn":"v. 使气馁，使畏缩，威吓","mean_en":"to make (someone) afraid or less confident","short_phrase":"","sentence":"The tall tree didn\u0027t daunt the cat from climbing it.","sentence_trans":"高树并没有使猫畏缩，它反而爬了上来。","sentence_audio":"sa_13_15436_0_2_20150808203358.aac","cloze_data":{"syllable":"daunt","cloze":"d[au]nt","options":["ae|ao|eu|ou|ow|a|o"],"tips":[["d[au]nting","d[au]ntless"]]}}