{"topic_id":5027,"word_level_id":1,"tag_id":0,"word":"difficulty","word_audio":"difficulty.mp3","word_variants":"difficulties","image_file":"4774_20120428_04_42_28_559.jpg","accent":"/ˈdɪfɪkəlti/","mean_cn":"n. 困难，难事，难点，经济拮据，分歧，麻烦","mean_en":"the quality of something that makes it hard to do; the difficult nature of something","word_etyma":"   ","short_phrase":"have some difficulty riding up the hill ","deformation_img":"d_1_5027_0_2_20150808123341.png","sentence":"I had some difficulties riding up the hill, but I made it.","sentence_trans":"我上坡的时候遇到些困难，但我还是成功登顶了！","sentence_phrase":"had some difficulties","sentence_audio":"sa_1_5027_0_2_20150808123341.aac","cloze_data":{"syllable":"dif-fi-cul-ty","cloze":"diffi-c[u]l-ty","options":["a|e|i|o"],"tips":[["c[u]lmy","c[u]lpa"]]}}