{"topic_id":8981,"word_level_id":2,"tag_id":0,"word":"affirm","word_audio":"affirm.mp3","word_variants":"affirmable,affirmably,affirmer,affirmed,affirming,affirms","image_file":"20120709_03_12_46_738.jpg","accent":"/əˈfɜːrm/","mean_cn":"v. 肯定；断定；坚持声称","mean_en":"to state firmly or publicly that something is true or that you support something strongly","word_etyma":"af一再+firm坚定→affirm肯定","short_phrase":"affirm his faith in the bible","deformation_img":"20140824_13_27_45_695_v3.png","sentence":"I\u0027ll affirm that I\u0027m telling the truth, your honor.","sentence_trans":"法官大人，我肯定我说的都是事实。","sentence_audio":"sa_2_8981_0_3_20150808155726.aac","cloze_data":{"syllable":"af-firm","cloze":"aff[ir]m","options":["ar|er|or|ur|a"],"tips":[["misaff[ir]m","disaff[ir]m"]]}}