{"topic_id":13214,"word_level_id":99,"tag_id":0,"word":"kitten","word_audio":"kitten.mp3","word_variants":"kittened,kittening,kittens","image_file":"i_99_13214_0_3_20150809022412.jpg","accent":"/ˈkɪtn/","mean_cn":"n. 小猫，小动物","mean_en":"","word_etyma":"kit\u003dcat猫+t+en表名词 → 小猫","sentence":"Cathy the cat just gave birth to kitty the kitten.","sentence_trans":"猫妈凯西刚生下的猫仔叫凯蒂。","sentence_audio":"sa_99_13214_0_3_20150809022412.aac","cloze_data":{"syllable":"kit-ten","cloze":"kitt[en]","options":["in|on|un|an|e|i|a|o|u"],"tips":[["kitt[en]dom","kitt[en]ish"]]}}