{"topic_id":5123,"word_level_id":1,"tag_id":0,"word":"valuable","word_audio":"wa_1_5123_0_2_20150808123529.aac","word_variants":"valuably,valuableness","image_file":"i_1_5123_0_2_20150808123529.jpg","accent":"/ˈvæljuəbl/","mean_cn":"adj. 贵重的，有价值的；  n. （复）贵重物品","mean_en":"worth a lot of money","word_etyma":"valu\u003dvalue价值+able形容词后缀→有价值的 ","short_phrase":"the valuable jewelery","deformation_img":"d_1_5123_0_2_20150808123529.png","sentence":"My grandfather left me valuable jewelery.","sentence_trans":"我的祖父留给我了贵重的珠宝。","sentence_phrase":"valuable jewelery","sentence_audio":"sa_1_5123_0_2_20150808123529.aac","cloze_data":{"syllable":"valu-able","cloze":"valu-a[ble]","options":["tle|dle|ple|cle|gle|kle"],"tips":[["ena[ble]","lia[ble]"]]}}