{"topic_id":14982,"word_level_id":2,"tag_id":0,"word":"herald","word_audio":"herald.mp3","word_variants":"heralded,heralding,heralds","image_file":"i_2_14982_0_3_20150808164602.jpg","accent":"/ˈherəld/","mean_cn":"n. 使节；传令官；通报者；先驱；预兆；  vt. 预告；宣布；为…欢呼","mean_en":"an official messenger in the past","short_phrase":"the King\u0027s heralds","deformation_img":"20140718_09_35_47_635_v3.png","sentence":"Here come the heralds. The king and queen must be right behind them.","sentence_trans":"使者到了，国王和皇后应该马上就到了。","sentence_audio":"sa_2_14982_0_3_20150808164602.aac","cloze_data":{"syllable":"her-ald","cloze":"her-[ald]","options":["alk|alm|alt|all|ial"],"tips":[["Ger[ald]","Don[ald]"]]}}