{"topic_id":15004,"word_level_id":12,"tag_id":0,"word":"shroud","word_audio":"shroud.mp3","word_variants":"shrouded,shrouding,shrouds","image_file":"i_12_15004_0_2_20150808182905.jpg","accent":"/ʃraʊd/","mean_cn":"n. 寿衣，覆盖物；  v. 覆盖，包以尸衣","mean_en":"a cloth that is used to wrap a dead body","sentence":"The dead body was hidden beneath a shroud.","sentence_trans":"尸体被遮掩在寿衣之下。","sentence_audio":"sa_12_15004_0_2_20150808182905.aac","cloze_data":{"syllable":"shroud","cloze":"[sh]roud","options":["tch|chr|sch|th"],"tips":[["en[sh]roud","[sh]rouded"]]}}