{"topic_id":6762,"word_level_id":1,"tag_id":0,"word":"sew","word_audio":"sew.mp3","word_variants":"sewable,sewed,sewn,sewing,sews","image_file":"i_1_6762_0_2_20150808125442.jpg","accent":"/soʊ/","mean_cn":"v. 缝，干针线活","mean_en":"to make or repair something (such as a piece of clothing) by using a needle and thread","short_phrase":"sew the cloth","deformation_img":"d_1_6762_0_2_20150808125442.png","sentence":"A sewing machine can sew so much faster than my hand.","sentence_trans":"缝纫机比手工缝制快多了。","sentence_audio":"sa_1_6762_0_2_20150808125442.aac","cloze_data":{"syllable":"sew","cloze":"s[ew]","options":["ia|eo|io|yr|i|a"],"tips":[["s[ew]er","res[ew]"]]}}