{"topic_id":19374,"word_level_id":18,"tag_id":0,"word":"ammeter","word_audio":"ammeter.mp3","image_file":"i_18_19374_0_2_20150808204227.jpg","accent":"/ˈæmiːtər/","mean_cn":"n. 【电】安培计，【电】电流计","mean_en":"a meter that measures the flow of electrical current in amperes","short_phrase":"measure electrical current with an ammeter","sentence":"An ammeter measures electrical current.","sentence_trans":"电流计测量电流。","sentence_audio":"sa_18_19374_0_2_20150808204227.aac","cloze_data":{"syllable":"am-me-ter","cloze":"amme-t[er]","options":["ar|ir|or|ur|a"],"tips":[["alt[er]","aft[er]"]]}}