{"topic_id":16568,"word_level_id":14,"tag_id":0,"word":"divestiture","word_audio":"divestiture.mp3","image_file":"20120906_03_12_13_694.jpg","accent":"/də\u0027vestətʃə/","mean_cn":"n. 剥夺，脱衣，拆分","mean_en":"the act of selling stock, property, etc., because of a government order","word_etyma":"di离开+vesti\u003dvest衣服 +ture表名词→使衣服离开 →脱衣，剥夺","short_phrase":"divestiture of losing stocks","sentence":"Our policies require divestiture of any stocks that don\u0027t perform well.","sentence_trans":"我们的政策要求我们脱掉任何景气不好的股。","sentence_audio":"sa_14_16568_0_2_20150808182227.aac","cloze_data":{"syllable":"di-vesti-ture","cloze":"di-vesti-t[ure]","options":["are|ere|ire|ore"],"tips":[["fut[ure]","act[ure]"]]}}