{"topic_id":4472,"word_level_id":1,"tag_id":0,"word":"bump","word_audio":"bump.mp3","word_variants":"bumped,bumping,bumps","image_file":"i_1_4472_0_4_20150808122812.jpg","accent":"/bʌmp/","mean_cn":"n. 隆起物，（碰撞造成的）肿块；  v. 撞击，颠簸地行驶，提高；  adv. 猛烈地","mean_en":"an area of skin that is raised because it was hit, injured, etc.","short_phrase":"      She rubs her baby bump.","deformation_img":"20141014_15_40_18_441_v3.png","sentence":"The woman rubs her baby bump.","sentence_trans":"这个女人在给她隆起的小腹擦东西。","sentence_phrase":"baby bump","sentence_audio":"sa_1_4472_0_4_20150808122812.aac","cloze_data":{"syllable":"bump","cloze":"b[u]mp","options":["a|e|i|o"],"tips":[["beb[u]mp","b[u]mping"]]}}