{"topic_id":1403,"word_level_id":11,"tag_id":0,"word":"hectic","word_audio":"hectic.mp3","image_file":"i_11_1403_0_6_20150808144509.jpg","accent":"/ˈhektɪk/","mean_cn":"adj. 紧张的，忙碌的，患肺病的，（因患肺病等）发烧的，有病态潮红的脸上发红，发热的，兴奋的，狂热的，肺病的","mean_en":"very busy and filled with activity","short_phrase":"a hectic work schedule","deformation_img":"20140907_15_32_41_757_v3.png","sentence":"She hopes to have more hands to end this hectic day!","sentence_trans":"她希望能多长几只手来终结这忙碌的一天！","sentence_phrase":"hectic day","sentence_audio":"sa_11_1403_0_6_20150808144509.aac","cloze_data":{"syllable":"hec-tic","cloze":"h[e]c-tic","options":["a|i|o|u"],"tips":[["h[e]ctor","h[e]ctical"]]}}