{"topic_id":9864,"word_level_id":2,"tag_id":0,"word":"rinse","word_audio":"rinse.mp3","word_variants":"rinsable,rinser,rinsed,rinsing,rinses","image_file":"i_2_9864_0_3_20150808162414.jpg","accent":"/rɪns/","mean_cn":"v. （用清水）刷，冲洗掉，漂净，漱口；  n. 嗽洗，漂洗，漂清，冲洗","mean_en":"to wash (something) with clean water and without soap","short_phrase":"rinse the dishes","deformation_img":"20140725_14_39_41_228_v3.png","sentence":"You should rinse the dishes before you put them in the dishwasher.","sentence_trans":"在把盘子放进洗碗机之前要先用清水冲洗一下。","sentence_phrase":"rinse the dishes","sentence_audio":"sa_2_9864_0_3_20150808162414.aac","cloze_data":{"syllable":"rinse","cloze":"r[in]se","options":["en|on|un|an|e|i|a|o|u"],"tips":[[]]}}