{"topic_id":3401,"word_level_id":9,"tag_id":0,"word":"carbonate","word_audio":"carbonate.mp3","word_variants":"carbonation,carbonated,carbonating,carbonates","image_file":"20120521_04_21_46_280.jpg","accent":"/ˈkɑːrbənət/","mean_cn":"n. 碳酸盐；  v. 使变成碳酸盐","mean_en":"a salt or ester of carbonic acid (containing the anion CO3)","word_etyma":"carbon碳+ate表化学名词→碳酸盐","short_phrase":"white powdery carbonate","sentence":"Carbonate usually looks like a white powder.","sentence_trans":"碳酸盐通常看起来像白色粉末。","sentence_audio":"sa_9_3401_0_2_20150808143805.aac","cloze_data":{"syllable":"car-bon-ate","cloze":"c[ar]-bon-ate","options":["er|ir|or|ur|a"],"tips":[["c[ar]bo","c[ar]"]]}}